anonymizer/__init__.py
anonymizer/anonymizer.py
anonymizer/assets/fonts/DINAlternate-Bold.ttf
anonymizer/assets/icons/create_icns.sh
anonymizer/assets/icons/kaleidoscope.png
anonymizer/assets/icons/kaleidoscope_flat.svg
anonymizer/assets/icons/kaleidoscope_stack_angle.svg
anonymizer/assets/icons/kaleidoscope_stack_vert.svg
anonymizer/assets/icons/pause.png
anonymizer/assets/icons/play.png
anonymizer/assets/icons/rsna_icon.icns
anonymizer/assets/icons/rsna_icon.ico
anonymizer/assets/icons/rsna_icon.png
anonymizer/assets/icons/rsna_logo_alpha.png
anonymizer/assets/icons/rsna_logo_head_profile.png
anonymizer/assets/icons/rsna_logo_head_profile_1024x1024.png
anonymizer/assets/icons/rsna_logo_head_profile_titled.png
anonymizer/assets/icons/rsna_titled_logo.svg
anonymizer/assets/icons/rsna_titled_logo_alpha.png
anonymizer/assets/icons/signpath_logo.svg
anonymizer/assets/locales/Pipfile
anonymizer/assets/locales/de/LC_MESSAGES/messages.mo
anonymizer/assets/locales/de/LC_MESSAGES/messages.po
anonymizer/assets/locales/de/LC_MESSAGES/messages.po~
anonymizer/assets/locales/de/html/1_übersicht.html
anonymizer/assets/locales/de/html/2_deidentifikationsprotokoll.html
anonymizer/assets/locales/de/html/3_anonymisierungsprojekte_verwalten.html
anonymizer/assets/locales/de/html/4_projekteinstellungen.html
anonymizer/assets/locales/de/html/5_bedienung.html
anonymizer/assets/locales/de/html/6_lizenz.html
anonymizer/assets/locales/de/html/images/AWSCognitoCredentials.png
anonymizer/assets/locales/de/html/images/AbfrageAbrufenImportieren.png
anonymizer/assets/locales/de/html/images/Auswahlabfrage.png
anonymizer/assets/locales/de/html/images/BildarchivQRServer.png
anonymizer/assets/locales/de/html/images/Dashboard.png
anonymizer/assets/locales/de/html/images/Dateiauswahloptionen.png
anonymizer/assets/locales/de/html/images/DateienImportieren.png
anonymizer/assets/locales/de/html/images/ExportServer.png
anonymizer/assets/locales/de/html/images/ExportStudienAWS.png
rsna_anonymizer-18.0.5.dist-info/METADATA
rsna_anonymizer-18.0.5.dist-info/WHEEL
rsna_anonymizer-18.0.5.dist-info/entry_points.txt
rsna_anonymizer-18.0.5.dist-info/licenses/LICENSE
rsna_anonymizer-18.0.5.dist-info/RECORD
