Metadata-Version: 2.4
Name: rsna-anonymizer
Version: 18.0.5
Summary: RSNA DICOM Anonymizer
License: RSNA-MIRC Public License
License-File: LICENSE
Author: Algorhythm Software
Author-email: michael@dx.life
Requires-Python: >=3.12.0,<3.13.0
Classifier: License :: Other/Proprietary License
Classifier: Programming Language :: Python :: 3
Classifier: Programming Language :: Python :: 3.12
Requires-Dist: bidict (>=0.23.1,<0.24.0)
Requires-Dist: boto3
Requires-Dist: click (>=8.1.8,<9.0.0)
Requires-Dist: cryptography
Requires-Dist: customtkinter
Requires-Dist: dataclasses-json (>=0.6.7,<0.7.0)
Requires-Dist: easyocr
Requires-Dist: ifaddr
Requires-Dist: numpy (<2.0.0)
Requires-Dist: opencv-python-headless
Requires-Dist: openpyxl
Requires-Dist: pillow
Requires-Dist: psutil
Requires-Dist: pydicom (>=2.4,<2.5)
Requires-Dist: pylibjpeg[all]
Requires-Dist: pynetdicom
Requires-Dist: requests
Requires-Dist: requests-oauthlib
Requires-Dist: sqlalchemy (>=2.0.38,<3.0.0)
Requires-Dist: tkhtmlview
Requires-Dist: toml (>=0.10.2,<0.11.0)
Project-URL: Homepage, https://github.com/RSNA/anonymizer
